tornado_mstp/__init__.py
tornado_mstp/client.py
tornado_mstp/handler.py
tornado_mstp/schema.py
tornado_mstp-0.1.1.dist-info/LICENSE
tornado_mstp-0.1.1.dist-info/METADATA
tornado_mstp-0.1.1.dist-info/WHEEL
tornado_mstp-0.1.1.dist-info/RECORD
