Metadata-Version: 2.1
Name: tornado-mstp
Version: 0.1.1
Summary: A tornado MSTP library, using WebSocket.
Author: Jackson
Author-email: jackson.zhang@mrs.ai
Requires-Python: >=3.11,<4.0
Classifier: Programming Language :: Python :: 3
Classifier: Programming Language :: Python :: 3.11
Requires-Dist: pydantic (>=2.1.1,<3.0.0)
Requires-Dist: pyrate-limiter (>=2.10.0,<3.0.0)
Requires-Dist: tornado (>=6.3.2,<7.0.0)
